[
  {
    "activityId": "1378",
    "title": "美团外卖企业媒体大新客激励活动-第10期",
    "metric": "amount",
    "date": "2026-07-07",
    "hour": 8,
    "slotMinute": 0,
    "dateHour": "2026-07-07 08:00",
    "recordedAt": "2026/7/7 08:26:25",
    "todayValidOrders": 254,
    "todayRedemptionOrders": 192,
    "todayActualPayment": 6255.32,
    "todayRedemptionAmount": 4856.88,
    "cumulativeRedemptionOrders": 192,
    "cumulativeRedemptionAmount": 4856.88
  },
  {
    "activityId": "1378",
    "title": "美团外卖企业媒体大新客激励活动-第10期",
    "metric": "amount",
    "date": "2026-07-07",
    "hour": 8,
    "slotMinute": 30,
    "dateHour": "2026-07-07 08:30",
    "recordedAt": "2026/7/7 08:49:33",
    "todayValidOrders": 271,
    "todayRedemptionOrders": 204,
    "todayActualPayment": 6620.33,
    "todayRedemptionAmount": 5103.66,
    "cumulativeRedemptionOrders": 204,
    "cumulativeRedemptionAmount": 5103.66
  },
  {
    "activityId": "1378",
    "title": "美团外卖企业媒体大新客激励活动-第10期",
    "metric": "amount",
    "date": "2026-07-07",
    "hour": 9,
    "slotMinute": 0,
    "dateHour": "2026-07-07 09:00",
    "recordedAt": "2026/7/7 09:24:19",
    "todayValidOrders": 302,
    "todayRedemptionOrders": 231,
    "todayActualPayment": 7432.77,
    "todayRedemptionAmount": 5644.84,
    "cumulativeRedemptionOrders": 231,
    "cumulativeRedemptionAmount": 5644.84
  },
  {
    "activityId": "1378",
    "title": "美团外卖企业媒体大新客激励活动-第10期",
    "metric": "amount",
    "date": "2026-07-07",
    "hour": 9,
    "slotMinute": 30,
    "dateHour": "2026-07-07 09:30",
    "recordedAt": "2026/7/7 09:59:01",
    "todayValidOrders": 362,
    "todayRedemptionOrders": 263,
    "todayActualPayment": 8924.45,
    "todayRedemptionAmount": 6242.93,
    "cumulativeRedemptionOrders": 263,
    "cumulativeRedemptionAmount": 6242.93
  },
  {
    "activityId": "1378",
    "title": "美团外卖企业媒体大新客激励活动-第10期",
    "metric": "amount",
    "date": "2026-07-07",
    "hour": 10,
    "slotMinute": 0,
    "dateHour": "2026-07-07 10:00",
    "recordedAt": "2026/7/7 10:22:12",
    "todayValidOrders": 426,
    "todayRedemptionOrders": 283,
    "todayActualPayment": 10779.4,
    "todayRedemptionAmount": 6613.62,
    "cumulativeRedemptionOrders": 283,
    "cumulativeRedemptionAmount": 6613.62
  },
  {
    "activityId": "1378",
    "title": "美团外卖企业媒体大新客激励活动-第10期",
    "metric": "amount",
    "date": "2026-07-07",
    "hour": 10,
    "slotMinute": 30,
    "dateHour": "2026-07-07 10:30",
    "recordedAt": "2026/7/7 10:56:52",
    "todayValidOrders": 606,
    "todayRedemptionOrders": 331,
    "todayActualPayment": 14932.88,
    "todayRedemptionAmount": 7842.47,
    "cumulativeRedemptionOrders": 331,
    "cumulativeRedemptionAmount": 7842.47
  },
  {
    "activityId": "1378",
    "title": "美团外卖企业媒体大新客激励活动-第10期",
    "metric": "amount",
    "date": "2026-07-07",
    "hour": 11,
    "slotMinute": 0,
    "dateHour": "2026-07-07 11:00",
    "recordedAt": "2026/7/7 11:20:05",
    "todayValidOrders": 867,
    "todayRedemptionOrders": 404,
    "todayActualPayment": 20438.09,
    "todayRedemptionAmount": 9499.17,
    "cumulativeRedemptionOrders": 404,
    "cumulativeRedemptionAmount": 9499.17
  },
  {
    "activityId": "1378",
    "title": "美团外卖企业媒体大新客激励活动-第10期",
    "metric": "amount",
    "date": "2026-07-07",
    "hour": 11,
    "slotMinute": 30,
    "dateHour": "2026-07-07 11:30",
    "recordedAt": "2026/7/7 11:54:43",
    "todayValidOrders": 1262,
    "todayRedemptionOrders": 629,
    "todayActualPayment": 29544.22,
    "todayRedemptionAmount": 14751.33,
    "cumulativeRedemptionOrders": 629,
    "cumulativeRedemptionAmount": 14751.33
  },
  {
    "activityId": "1378",
    "title": "美团外卖企业媒体大新客激励活动-第10期",
    "metric": "amount",
    "date": "2026-07-07",
    "hour": 12,
    "slotMinute": 0,
    "dateHour": "2026-07-07 12:00",
    "recordedAt": "2026/7/7 12:29:38",
    "todayValidOrders": 1566,
    "todayRedemptionOrders": 990,
    "todayActualPayment": 36823.28,
    "todayRedemptionAmount": 22609.6,
    "cumulativeRedemptionOrders": 990,
    "cumulativeRedemptionAmount": 22609.6
  },
  {
    "activityId": "1378",
    "title": "美团外卖企业媒体大新客激励活动-第10期",
    "metric": "amount",
    "date": "2026-07-07",
    "hour": 12,
    "slotMinute": 30,
    "dateHour": "2026-07-07 12:30",
    "recordedAt": "2026/7/7 12:53:19",
    "todayValidOrders": 1744,
    "todayRedemptionOrders": 1233,
    "todayActualPayment": 40707.05,
    "todayRedemptionAmount": 27927.73,
    "cumulativeRedemptionOrders": 1233,
    "cumulativeRedemptionAmount": 27927.73
  },
  {
    "activityId": "1378",
    "title": "美团外卖企业媒体大新客激励活动-第10期",
    "metric": "amount",
    "date": "2026-07-07",
    "hour": 13,
    "slotMinute": 0,
    "dateHour": "2026-07-07 13:00",
    "recordedAt": "2026/7/7 13:17:02",
    "todayValidOrders": 1871,
    "todayRedemptionOrders": 1421,
    "todayActualPayment": 43683.05,
    "todayRedemptionAmount": 32428.55,
    "cumulativeRedemptionOrders": 1421,
    "cumulativeRedemptionAmount": 32428.55
  },
  {
    "activityId": "1378",
    "title": "美团外卖企业媒体大新客激励活动-第10期",
    "metric": "amount",
    "date": "2026-07-07",
    "hour": 13,
    "slotMinute": 30,
    "dateHour": "2026-07-07 13:30",
    "recordedAt": "2026/7/7 13:53:49",
    "todayValidOrders": 2014,
    "todayRedemptionOrders": 1640,
    "todayActualPayment": 47170.84,
    "todayRedemptionAmount": 37151.1,
    "cumulativeRedemptionOrders": 1640,
    "cumulativeRedemptionAmount": 37151.1
  },
  {
    "activityId": "1378",
    "title": "美团外卖企业媒体大新客激励活动-第10期",
    "metric": "amount",
    "date": "2026-07-07",
    "hour": 14,
    "slotMinute": 0,
    "dateHour": "2026-07-07 14:00",
    "recordedAt": "2026/7/7 14:28:25",
    "todayValidOrders": 2132,
    "todayRedemptionOrders": 1774,
    "todayActualPayment": 50310.05,
    "todayRedemptionAmount": 40154.87,
    "cumulativeRedemptionOrders": 1774,
    "cumulativeRedemptionAmount": 40154.87
  },
  {
    "activityId": "1378",
    "title": "美团外卖企业媒体大新客激励活动-第10期",
    "metric": "amount",
    "date": "2026-07-07",
    "hour": 14,
    "slotMinute": 30,
    "dateHour": "2026-07-07 14:30",
    "recordedAt": "2026/7/7 14:51:55",
    "todayValidOrders": 2204,
    "todayRedemptionOrders": 1837,
    "todayActualPayment": 52222.63,
    "todayRedemptionAmount": 41917.57,
    "cumulativeRedemptionOrders": 1837,
    "cumulativeRedemptionAmount": 41917.57
  },
  {
    "activityId": "1378",
    "title": "美团外卖企业媒体大新客激励活动-第10期",
    "metric": "amount",
    "date": "2026-07-07",
    "hour": 15,
    "slotMinute": 0,
    "dateHour": "2026-07-07 15:00",
    "recordedAt": "2026/7/7 15:27:22",
    "todayValidOrders": 2300,
    "todayRedemptionOrders": 1943,
    "todayActualPayment": 54444.11,
    "todayRedemptionAmount": 44559.53,
    "cumulativeRedemptionOrders": 1943,
    "cumulativeRedemptionAmount": 44559.53
  },
  {
    "activityId": "1378",
    "title": "美团外卖企业媒体大新客激励活动-第10期",
    "metric": "amount",
    "date": "2026-07-07",
    "hour": 15,
    "slotMinute": 30,
    "dateHour": "2026-07-07 15:30",
    "recordedAt": "2026/7/7 15:50:59",
    "todayValidOrders": 2360,
    "todayRedemptionOrders": 2013,
    "todayActualPayment": 56003.3,
    "todayRedemptionAmount": 46350.52,
    "cumulativeRedemptionOrders": 2013,
    "cumulativeRedemptionAmount": 46350.52
  },
  {
    "activityId": "1378",
    "title": "美团外卖企业媒体大新客激励活动-第10期",
    "metric": "amount",
    "date": "2026-07-07",
    "hour": 16,
    "slotMinute": 0,
    "dateHour": "2026-07-07 16:00",
    "recordedAt": "2026/7/7 16:26:18",
    "todayValidOrders": 2454,
    "todayRedemptionOrders": 2159,
    "todayActualPayment": 58034.45,
    "todayRedemptionAmount": 49895.95,
    "cumulativeRedemptionOrders": 2159,
    "cumulativeRedemptionAmount": 49895.95
  },
  {
    "activityId": "1378",
    "title": "美团外卖企业媒体大新客激励活动-第10期",
    "metric": "amount",
    "date": "2026-07-07",
    "hour": 16,
    "slotMinute": 30,
    "dateHour": "2026-07-07 16:30",
    "recordedAt": "2026/7/7 16:49:27",
    "todayValidOrders": 2542,
    "todayRedemptionOrders": 2226,
    "todayActualPayment": 60632.33,
    "todayRedemptionAmount": 51383.95,
    "cumulativeRedemptionOrders": 2226,
    "cumulativeRedemptionAmount": 51383.95
  },
  {
    "activityId": "1378",
    "title": "美团外卖企业媒体大新客激励活动-第10期",
    "metric": "amount",
    "date": "2026-07-07",
    "hour": 17,
    "slotMinute": 0,
    "dateHour": "2026-07-07 17:00",
    "recordedAt": "2026/7/7 17:24:10",
    "todayValidOrders": 2715,
    "todayRedemptionOrders": 2322,
    "todayActualPayment": 64525,
    "todayRedemptionAmount": 53566.96,
    "cumulativeRedemptionOrders": 2322,
    "cumulativeRedemptionAmount": 53566.96
  },
  {
    "activityId": "1378",
    "title": "美团外卖企业媒体大新客激励活动-第10期",
    "metric": "amount",
    "date": "2026-07-07",
    "hour": 17,
    "slotMinute": 30,
    "dateHour": "2026-07-07 17:30",
    "recordedAt": "2026/7/7 17:58:43",
    "todayValidOrders": 2962,
    "todayRedemptionOrders": 2459,
    "todayActualPayment": 70421.15,
    "todayRedemptionAmount": 56370.65,
    "cumulativeRedemptionOrders": 2459,
    "cumulativeRedemptionAmount": 56370.65
  },
  {
    "activityId": "1378",
    "title": "美团外卖企业媒体大新客激励活动-第10期",
    "metric": "amount",
    "date": "2026-07-07",
    "hour": 18,
    "slotMinute": 0,
    "dateHour": "2026-07-07 18:00",
    "recordedAt": "2026/7/7 18:21:42",
    "todayValidOrders": 3111,
    "todayRedemptionOrders": 2600,
    "todayActualPayment": 74916.53,
    "todayRedemptionAmount": 60429.46,
    "cumulativeRedemptionOrders": 2600,
    "cumulativeRedemptionAmount": 60429.46
  },
  {
    "activityId": "1378",
    "title": "美团外卖企业媒体大新客激励活动-第10期",
    "metric": "amount",
    "date": "2026-07-07",
    "hour": 18,
    "slotMinute": 30,
    "dateHour": "2026-07-07 18:30",
    "recordedAt": "2026/7/7 18:56:17",
    "todayValidOrders": 3347,
    "todayRedemptionOrders": 2807,
    "todayActualPayment": 80878.94,
    "todayRedemptionAmount": 65879.64,
    "cumulativeRedemptionOrders": 2807,
    "cumulativeRedemptionAmount": 65879.64
  },
  {
    "activityId": "1378",
    "title": "美团外卖企业媒体大新客激励活动-第10期",
    "metric": "amount",
    "date": "2026-07-07",
    "hour": 19,
    "slotMinute": 0,
    "dateHour": "2026-07-07 19:00",
    "recordedAt": "2026/7/7 19:19:20",
    "todayValidOrders": 3479,
    "todayRedemptionOrders": 2961,
    "todayActualPayment": 84026.72,
    "todayRedemptionAmount": 69974.18,
    "cumulativeRedemptionOrders": 2961,
    "cumulativeRedemptionAmount": 69974.18
  },
  {
    "activityId": "1378",
    "title": "美团外卖企业媒体大新客激励活动-第10期",
    "metric": "amount",
    "date": "2026-07-07",
    "hour": 19,
    "slotMinute": 30,
    "dateHour": "2026-07-07 19:30",
    "recordedAt": "2026/7/7 19:53:53",
    "todayValidOrders": 3667,
    "todayRedemptionOrders": 3165,
    "todayActualPayment": 88485.04,
    "todayRedemptionAmount": 75048.9,
    "cumulativeRedemptionOrders": 3165,
    "cumulativeRedemptionAmount": 75048.9
  },
  {
    "activityId": "1378",
    "title": "美团外卖企业媒体大新客激励活动-第10期",
    "metric": "amount",
    "date": "2026-07-07",
    "hour": 20,
    "slotMinute": 0,
    "dateHour": "2026-07-07 20:00",
    "recordedAt": "2026/7/7 20:28:27",
    "todayValidOrders": 3832,
    "todayRedemptionOrders": 3343,
    "todayActualPayment": 92366.85,
    "todayRedemptionAmount": 79419.08,
    "cumulativeRedemptionOrders": 3343,
    "cumulativeRedemptionAmount": 79419.08
  },
  {
    "activityId": "1378",
    "title": "美团外卖企业媒体大新客激励活动-第10期",
    "metric": "amount",
    "date": "2026-07-07",
    "hour": 20,
    "slotMinute": 30,
    "dateHour": "2026-07-07 20:30",
    "recordedAt": "2026/7/7 20:51:29",
    "todayValidOrders": 3918,
    "todayRedemptionOrders": 3467,
    "todayActualPayment": 94603.94,
    "todayRedemptionAmount": 82277.68,
    "cumulativeRedemptionOrders": 3467,
    "cumulativeRedemptionAmount": 82277.68
  },
  {
    "activityId": "1378",
    "title": "美团外卖企业媒体大新客激励活动-第10期",
    "metric": "amount",
    "date": "2026-07-07",
    "hour": 21,
    "slotMinute": 0,
    "dateHour": "2026-07-07 21:00",
    "recordedAt": "2026/7/7 21:03:01",
    "todayValidOrders": 3963,
    "todayRedemptionOrders": 3524,
    "todayActualPayment": 95696.41,
    "todayRedemptionAmount": 84020.08,
    "cumulativeRedemptionOrders": 3524,
    "cumulativeRedemptionAmount": 84020.08
  },
  {
    "activityId": "1378",
    "title": "美团外卖企业媒体大新客激励活动-第10期",
    "metric": "amount",
    "date": "2026-07-08",
    "hour": 11,
    "slotMinute": 0,
    "dateHour": "2026-07-08 11:00",
    "recordedAt": "2026/7/8 11:19:18",
    "todayValidOrders": 929,
    "todayRedemptionOrders": 372,
    "todayActualPayment": 21811.44,
    "todayRedemptionAmount": 8214.5,
    "cumulativeRedemptionOrders": 4749,
    "cumulativeRedemptionAmount": 115682
  },
  {
    "activityId": "1378",
    "title": "美团外卖企业媒体大新客激励活动-第10期",
    "metric": "amount",
    "date": "2026-07-08",
    "hour": 11,
    "slotMinute": 30,
    "dateHour": "2026-07-08 11:30",
    "recordedAt": "2026/7/8 11:54:20",
    "todayValidOrders": 1316,
    "todayRedemptionOrders": 647,
    "todayActualPayment": 30535.76,
    "todayRedemptionAmount": 14372.98,
    "cumulativeRedemptionOrders": 5028,
    "cumulativeRedemptionAmount": 121903.5
  },
  {
    "activityId": "1378",
    "title": "美团外卖企业媒体大新客激励活动-第10期",
    "metric": "amount",
    "date": "2026-07-08",
    "hour": 12,
    "slotMinute": 0,
    "dateHour": "2026-07-08 12:00",
    "recordedAt": "2026/7/8 12:29:26",
    "todayValidOrders": 1618,
    "todayRedemptionOrders": 1019,
    "todayActualPayment": 37567.4,
    "todayRedemptionAmount": 22435.2,
    "cumulativeRedemptionOrders": 5404,
    "cumulativeRedemptionAmount": 130037.29
  },
  {
    "activityId": "1378",
    "title": "美团外卖企业媒体大新客激励活动-第10期",
    "metric": "amount",
    "date": "2026-07-08",
    "hour": 12,
    "slotMinute": 30,
    "dateHour": "2026-07-08 12:30",
    "recordedAt": "2026/7/8 12:53:18",
    "todayValidOrders": 1781,
    "todayRedemptionOrders": 1244,
    "todayActualPayment": 41614.39,
    "todayRedemptionAmount": 27530.61,
    "cumulativeRedemptionOrders": 5635,
    "cumulativeRedemptionAmount": 135239.47999999998
  },
  {
    "activityId": "1378",
    "title": "美团外卖企业媒体大新客激励活动-第10期",
    "metric": "amount",
    "date": "2026-07-08",
    "hour": 13,
    "slotMinute": 0,
    "dateHour": "2026-07-08 13:00",
    "recordedAt": "2026/7/8 13:28:56",
    "todayValidOrders": 1935,
    "todayRedemptionOrders": 1520,
    "todayActualPayment": 45026.97,
    "todayRedemptionAmount": 33843.73,
    "cumulativeRedemptionOrders": 5914,
    "cumulativeRedemptionAmount": 141612.38
  },
  {
    "activityId": "1378",
    "title": "美团外卖企业媒体大新客激励活动-第10期",
    "metric": "amount",
    "date": "2026-07-08",
    "hour": 13,
    "slotMinute": 30,
    "dateHour": "2026-07-08 13:30",
    "recordedAt": "2026/7/8 13:52:09",
    "todayValidOrders": 2010,
    "todayRedemptionOrders": 1644,
    "todayActualPayment": 46717.63,
    "todayRedemptionAmount": 36582.19,
    "cumulativeRedemptionOrders": 6038,
    "cumulativeRedemptionAmount": 144350.84
  },
  {
    "activityId": "1378",
    "title": "美团外卖企业媒体大新客激励活动-第10期",
    "metric": "amount",
    "date": "2026-07-08",
    "hour": 14,
    "slotMinute": 0,
    "dateHour": "2026-07-08 14:00",
    "recordedAt": "2026/7/8 14:26:51",
    "todayValidOrders": 2138,
    "todayRedemptionOrders": 1766,
    "todayActualPayment": 50154.66,
    "todayRedemptionAmount": 39313.08,
    "cumulativeRedemptionOrders": 6161,
    "cumulativeRedemptionAmount": 147094.72999999998
  },
  {
    "activityId": "1378",
    "title": "美团外卖企业媒体大新客激励活动-第10期",
    "metric": "amount",
    "date": "2026-07-08",
    "hour": 14,
    "slotMinute": 30,
    "dateHour": "2026-07-08 14:30",
    "recordedAt": "2026/7/8 14:49:57",
    "todayValidOrders": 2235,
    "todayRedemptionOrders": 1849,
    "todayActualPayment": 52442.19,
    "todayRedemptionAmount": 41600.26,
    "cumulativeRedemptionOrders": 6244,
    "cumulativeRedemptionAmount": 149354.01
  },
  {
    "activityId": "1378",
    "title": "美团外卖企业媒体大新客激励活动-第10期",
    "metric": "amount",
    "date": "2026-07-08",
    "hour": 15,
    "slotMinute": 0,
    "dateHour": "2026-07-08 15:00",
    "recordedAt": "2026/7/8 15:24:38",
    "todayValidOrders": 2377,
    "todayRedemptionOrders": 1970,
    "todayActualPayment": 55750.72,
    "todayRedemptionAmount": 44576.91,
    "cumulativeRedemptionOrders": 6366,
    "cumulativeRedemptionAmount": 152354.06
  },
  {
    "activityId": "1378",
    "title": "美团外卖企业媒体大新客激励活动-第10期",
    "metric": "amount",
    "date": "2026-07-08",
    "hour": 15,
    "slotMinute": 30,
    "dateHour": "2026-07-08 15:30",
    "recordedAt": "2026/7/8 15:59:13",
    "todayValidOrders": 2497,
    "todayRedemptionOrders": 2125,
    "todayActualPayment": 58593.05,
    "todayRedemptionAmount": 48331.71,
    "cumulativeRedemptionOrders": 6524,
    "cumulativeRedemptionAmount": 156245.24
  },
  {
    "activityId": "1378",
    "title": "美团外卖企业媒体大新客激励活动-第10期",
    "metric": "amount",
    "date": "2026-07-08",
    "hour": 16,
    "slotMinute": 0,
    "dateHour": "2026-07-08 16:00",
    "recordedAt": "2026/7/8 16:22:23",
    "todayValidOrders": 2597,
    "todayRedemptionOrders": 2258,
    "todayActualPayment": 61071.35,
    "todayRedemptionAmount": 51327.64,
    "cumulativeRedemptionOrders": 6660,
    "cumulativeRedemptionAmount": 159336.07
  },
  {
    "activityId": "1378",
    "title": "美团外卖企业媒体大新客激励活动-第10期",
    "metric": "amount",
    "date": "2026-07-08",
    "hour": 16,
    "slotMinute": 30,
    "dateHour": "2026-07-08 16:30",
    "recordedAt": "2026/7/8 16:57:07",
    "todayValidOrders": 2729,
    "todayRedemptionOrders": 2396,
    "todayActualPayment": 64437.45,
    "todayRedemptionAmount": 54806.38,
    "cumulativeRedemptionOrders": 6798,
    "cumulativeRedemptionAmount": 162814.81
  },
  {
    "activityId": "1378",
    "title": "美团外卖企业媒体大新客激励活动-第10期",
    "metric": "amount",
    "date": "2026-07-08",
    "hour": 17,
    "slotMinute": 0,
    "dateHour": "2026-07-08 17:00",
    "recordedAt": "2026/7/8 17:20:17",
    "todayValidOrders": 2857,
    "todayRedemptionOrders": 2477,
    "todayActualPayment": 67726.34,
    "todayRedemptionAmount": 56707.5,
    "cumulativeRedemptionOrders": 6880,
    "cumulativeRedemptionAmount": 164727.01
  },
  {
    "activityId": "1378",
    "title": "美团外卖企业媒体大新客激励活动-第10期",
    "metric": "amount",
    "date": "2026-07-08",
    "hour": 17,
    "slotMinute": 30,
    "dateHour": "2026-07-08 17:30",
    "recordedAt": "2026/7/8 17:54:54",
    "todayValidOrders": 3069,
    "todayRedemptionOrders": 2621,
    "todayActualPayment": 73946.2,
    "todayRedemptionAmount": 60004.82,
    "cumulativeRedemptionOrders": 7024,
    "cumulativeRedemptionAmount": 168024.33
  },
  {
    "activityId": "1378",
    "title": "美团外卖企业媒体大新客激励活动-第10期",
    "metric": "amount",
    "date": "2026-07-08",
    "hour": 18,
    "slotMinute": 0,
    "dateHour": "2026-07-08 18:00",
    "recordedAt": "2026/7/8 18:29:35",
    "todayValidOrders": 3310,
    "todayRedemptionOrders": 2806,
    "todayActualPayment": 80599.42,
    "todayRedemptionAmount": 65107.31,
    "cumulativeRedemptionOrders": 7211,
    "cumulativeRedemptionAmount": 173154.05
  },
  {
    "activityId": "1378",
    "title": "美团外卖企业媒体大新客激励活动-第10期",
    "metric": "amount",
    "date": "2026-07-08",
    "hour": 18,
    "slotMinute": 30,
    "dateHour": "2026-07-08 18:30",
    "recordedAt": "2026/7/8 18:47:37",
    "todayValidOrders": 3421,
    "todayRedemptionOrders": 2921,
    "todayActualPayment": 83354.03,
    "todayRedemptionAmount": 68084.34,
    "cumulativeRedemptionOrders": 7330,
    "cumulativeRedemptionAmount": 176230.36
  }
]