[
  {
    "activityId": "1323",
    "title": "【买药享好价】企业媒体合作冲锋激励赛",
    "metric": "orders",
    "date": "2026-06-29",
    "hour": 11,
    "slotMinute": 30,
    "dateHour": "2026-06-29 11:30",
    "recordedAt": "2026/6/29 11:57:01",
    "todayValidOrders": 82,
    "todayRedemptionOrders": 57,
    "todayActualPayment": 2067.26,
    "todayRedemptionAmount": 1079.85,
    "cumulativeRedemptionOrders": 648,
    "cumulativeRedemptionAmount": 12050.24
  },
  {
    "activityId": "1323",
    "title": "【买药享好价】企业媒体合作冲锋激励赛",
    "metric": "orders",
    "date": "2026-06-29",
    "hour": 12,
    "slotMinute": 0,
    "dateHour": "2026-06-29 12:00",
    "recordedAt": "2026/6/29 12:25:55",
    "todayValidOrders": 85,
    "todayRedemptionOrders": 62,
    "todayActualPayment": 2142.27,
    "todayRedemptionAmount": 1224.73,
    "cumulativeRedemptionOrders": 653,
    "cumulativeRedemptionAmount": 12195.119999999999
  },
  {
    "activityId": "1323",
    "title": "【买药享好价】企业媒体合作冲锋激励赛",
    "metric": "orders",
    "date": "2026-06-29",
    "hour": 12,
    "slotMinute": 30,
    "dateHour": "2026-06-29 12:30",
    "recordedAt": "2026/6/29 12:57:48",
    "todayValidOrders": 103,
    "todayRedemptionOrders": 69,
    "todayActualPayment": 2384.07,
    "todayRedemptionAmount": 1372.28,
    "cumulativeRedemptionOrders": 660,
    "cumulativeRedemptionAmount": 12342.67
  },
  {
    "activityId": "1323",
    "title": "【买药享好价】企业媒体合作冲锋激励赛",
    "metric": "orders",
    "date": "2026-06-29",
    "hour": 13,
    "slotMinute": 0,
    "dateHour": "2026-06-29 13:00",
    "recordedAt": "2026/6/29 13:29:44",
    "todayValidOrders": 108,
    "todayRedemptionOrders": 85,
    "todayActualPayment": 2456.87,
    "todayRedemptionAmount": 1564.36,
    "cumulativeRedemptionOrders": 676,
    "cumulativeRedemptionAmount": 12534.75
  },
  {
    "activityId": "1323",
    "title": "【买药享好价】企业媒体合作冲锋激励赛",
    "metric": "orders",
    "date": "2026-06-29",
    "hour": 13,
    "slotMinute": 30,
    "dateHour": "2026-06-29 13:30",
    "recordedAt": "2026/6/29 13:50:58",
    "todayValidOrders": 108,
    "todayRedemptionOrders": 87,
    "todayActualPayment": 2456.87,
    "todayRedemptionAmount": 1603.61,
    "cumulativeRedemptionOrders": 678,
    "cumulativeRedemptionAmount": 12574
  },
  {
    "activityId": "1323",
    "title": "【买药享好价】企业媒体合作冲锋激励赛",
    "metric": "orders",
    "date": "2026-06-29",
    "hour": 14,
    "slotMinute": 0,
    "dateHour": "2026-06-29 14:00",
    "recordedAt": "2026/6/29 14:24:07",
    "todayValidOrders": 116,
    "todayRedemptionOrders": 92,
    "todayActualPayment": 2663.81,
    "todayRedemptionAmount": 1752.29,
    "cumulativeRedemptionOrders": 683,
    "cumulativeRedemptionAmount": 12722.68
  },
  {
    "activityId": "1323",
    "title": "【买药享好价】企业媒体合作冲锋激励赛",
    "metric": "orders",
    "date": "2026-06-29",
    "hour": 14,
    "slotMinute": 30,
    "dateHour": "2026-06-29 14:30",
    "recordedAt": "2026/6/29 14:56:23",
    "todayValidOrders": 118,
    "todayRedemptionOrders": 97,
    "todayActualPayment": 2730.83,
    "todayRedemptionAmount": 1830.03,
    "cumulativeRedemptionOrders": 688,
    "cumulativeRedemptionAmount": 12800.42
  },
  {
    "activityId": "1323",
    "title": "【买药享好价】企业媒体合作冲锋激励赛",
    "metric": "orders",
    "date": "2026-06-29",
    "hour": 15,
    "slotMinute": 0,
    "dateHour": "2026-06-29 15:00",
    "recordedAt": "2026/6/29 15:28:18",
    "todayValidOrders": 137,
    "todayRedemptionOrders": 105,
    "todayActualPayment": 3030.11,
    "todayRedemptionAmount": 2024.76,
    "cumulativeRedemptionOrders": 696,
    "cumulativeRedemptionAmount": 12995.15
  },
  {
    "activityId": "1323",
    "title": "【买药享好价】企业媒体合作冲锋激励赛",
    "metric": "orders",
    "date": "2026-06-29",
    "hour": 15,
    "slotMinute": 30,
    "dateHour": "2026-06-29 15:30",
    "recordedAt": "2026/6/29 15:49:34",
    "todayValidOrders": 138,
    "todayRedemptionOrders": 110,
    "todayActualPayment": 3050.12,
    "todayRedemptionAmount": 2137.35,
    "cumulativeRedemptionOrders": 701,
    "cumulativeRedemptionAmount": 13107.74
  },
  {
    "activityId": "1323",
    "title": "【买药享好价】企业媒体合作冲锋激励赛",
    "metric": "orders",
    "date": "2026-06-29",
    "hour": 16,
    "slotMinute": 0,
    "dateHour": "2026-06-29 16:00",
    "recordedAt": "2026/6/29 16:10:51",
    "todayValidOrders": 140,
    "todayRedemptionOrders": 116,
    "todayActualPayment": 3094.63,
    "todayRedemptionAmount": 2227.86,
    "cumulativeRedemptionOrders": 707,
    "cumulativeRedemptionAmount": 13198.25
  }
]