[
  {
    "activityId": "1498",
    "title": "7.24~7.26【美团闪购】水果企业单单奖励",
    "metric": "orders",
    "date": "2026-07-24",
    "hour": 8,
    "slotMinute": 0,
    "dateHour": "2026-07-24 08:00",
    "recordedAt": "2026/7/24 08:18:26",
    "todayValidOrders": 7,
    "todayRedemptionOrders": 2,
    "todayActualPayment": 344.59,
    "todayRedemptionAmount": 75.79,
    "cumulativeRedemptionOrders": 2,
    "cumulativeRedemptionAmount": 75.79
  },
  {
    "activityId": "1498",
    "title": "7.24~7.26【美团闪购】水果企业单单奖励",
    "metric": "orders",
    "date": "2026-07-24",
    "hour": 8,
    "slotMinute": 30,
    "dateHour": "2026-07-24 08:30",
    "recordedAt": "2026/7/24 08:46:41",
    "todayValidOrders": 8,
    "todayRedemptionOrders": 4,
    "todayActualPayment": 398.69,
    "todayRedemptionAmount": 179.59,
    "cumulativeRedemptionOrders": 4,
    "cumulativeRedemptionAmount": 179.59
  },
  {
    "activityId": "1498",
    "title": "7.24~7.26【美团闪购】水果企业单单奖励",
    "metric": "orders",
    "date": "2026-07-24",
    "hour": 9,
    "slotMinute": 0,
    "dateHour": "2026-07-24 09:00",
    "recordedAt": "2026/7/24 09:29:16",
    "todayValidOrders": 13,
    "todayRedemptionOrders": 5,
    "todayActualPayment": 638.11,
    "todayRedemptionAmount": 233.69,
    "cumulativeRedemptionOrders": 5,
    "cumulativeRedemptionAmount": 233.69
  },
  {
    "activityId": "1498",
    "title": "7.24~7.26【美团闪购】水果企业单单奖励",
    "metric": "orders",
    "date": "2026-07-24",
    "hour": 9,
    "slotMinute": 30,
    "dateHour": "2026-07-24 09:30",
    "recordedAt": "2026/7/24 09:57:28",
    "todayValidOrders": 17,
    "todayRedemptionOrders": 7,
    "todayActualPayment": 851.63,
    "todayRedemptionAmount": 271.41,
    "cumulativeRedemptionOrders": 7,
    "cumulativeRedemptionAmount": 271.41
  },
  {
    "activityId": "1498",
    "title": "7.24~7.26【美团闪购】水果企业单单奖励",
    "metric": "orders",
    "date": "2026-07-24",
    "hour": 10,
    "slotMinute": 0,
    "dateHour": "2026-07-24 10:00",
    "recordedAt": "2026/7/24 10:25:56",
    "todayValidOrders": 23,
    "todayRedemptionOrders": 10,
    "todayActualPayment": 1072.79,
    "todayRedemptionAmount": 476.61,
    "cumulativeRedemptionOrders": 10,
    "cumulativeRedemptionAmount": 476.61
  },
  {
    "activityId": "1498",
    "title": "7.24~7.26【美团闪购】水果企业单单奖励",
    "metric": "orders",
    "date": "2026-07-24",
    "hour": 10,
    "slotMinute": 30,
    "dateHour": "2026-07-24 10:30",
    "recordedAt": "2026/7/24 10:54:14",
    "todayValidOrders": 24,
    "todayRedemptionOrders": 15,
    "todayActualPayment": 1084.14,
    "todayRedemptionAmount": 667.82,
    "cumulativeRedemptionOrders": 15,
    "cumulativeRedemptionAmount": 667.82
  },
  {
    "activityId": "1498",
    "title": "7.24~7.26【美团闪购】水果企业单单奖励",
    "metric": "orders",
    "date": "2026-07-24",
    "hour": 11,
    "slotMinute": 0,
    "dateHour": "2026-07-24 11:00",
    "recordedAt": "2026/7/24 11:22:38",
    "todayValidOrders": 25,
    "todayRedemptionOrders": 17,
    "todayActualPayment": 1179.14,
    "todayRedemptionAmount": 724.42,
    "cumulativeRedemptionOrders": 17,
    "cumulativeRedemptionAmount": 724.42
  },
  {
    "activityId": "1498",
    "title": "7.24~7.26【美团闪购】水果企业单单奖励",
    "metric": "orders",
    "date": "2026-07-24",
    "hour": 11,
    "slotMinute": 30,
    "dateHour": "2026-07-24 11:30",
    "recordedAt": "2026/7/24 11:36:52",
    "todayValidOrders": 26,
    "todayRedemptionOrders": 18,
    "todayActualPayment": 1279.94,
    "todayRedemptionAmount": 735.77,
    "cumulativeRedemptionOrders": 18,
    "cumulativeRedemptionAmount": 735.77
  }
]