[
  {
    "activityId": "1448",
    "title": "美团外卖企业媒体大新客激励活动-第12期",
    "metric": "amount",
    "date": "2026-07-21",
    "hour": 8,
    "slotMinute": 0,
    "dateHour": "2026-07-21 08:00",
    "recordedAt": "2026/7/21 08:24:25",
    "todayValidOrders": 217,
    "todayRedemptionOrders": 177,
    "todayActualPayment": 5433.86,
    "todayRedemptionAmount": 4428.31,
    "cumulativeRedemptionOrders": 177,
    "cumulativeRedemptionAmount": 4428.31
  },
  {
    "activityId": "1448",
    "title": "美团外卖企业媒体大新客激励活动-第12期",
    "metric": "amount",
    "date": "2026-07-21",
    "hour": 8,
    "slotMinute": 30,
    "dateHour": "2026-07-21 08:30",
    "recordedAt": "2026/7/21 08:50:59",
    "todayValidOrders": 242,
    "todayRedemptionOrders": 188,
    "todayActualPayment": 6046.06,
    "todayRedemptionAmount": 4729.69,
    "cumulativeRedemptionOrders": 188,
    "cumulativeRedemptionAmount": 4729.69
  },
  {
    "activityId": "1448",
    "title": "美团外卖企业媒体大新客激励活动-第12期",
    "metric": "amount",
    "date": "2026-07-21",
    "hour": 9,
    "slotMinute": 0,
    "dateHour": "2026-07-21 09:00",
    "recordedAt": "2026/7/21 09:17:38",
    "todayValidOrders": 271,
    "todayRedemptionOrders": 210,
    "todayActualPayment": 6764.23,
    "todayRedemptionAmount": 5217.91,
    "cumulativeRedemptionOrders": 210,
    "cumulativeRedemptionAmount": 5217.91
  },
  {
    "activityId": "1448",
    "title": "美团外卖企业媒体大新客激励活动-第12期",
    "metric": "amount",
    "date": "2026-07-21",
    "hour": 9,
    "slotMinute": 30,
    "dateHour": "2026-07-21 09:30",
    "recordedAt": "2026/7/21 09:57:29",
    "todayValidOrders": 334,
    "todayRedemptionOrders": 240,
    "todayActualPayment": 8548.74,
    "todayRedemptionAmount": 5792.39,
    "cumulativeRedemptionOrders": 240,
    "cumulativeRedemptionAmount": 5792.39
  },
  {
    "activityId": "1448",
    "title": "美团外卖企业媒体大新客激励活动-第12期",
    "metric": "amount",
    "date": "2026-07-21",
    "hour": 10,
    "slotMinute": 0,
    "dateHour": "2026-07-21 10:00",
    "recordedAt": "2026/7/21 10:24:04",
    "todayValidOrders": 399,
    "todayRedemptionOrders": 267,
    "todayActualPayment": 10267,
    "todayRedemptionAmount": 6324.48,
    "cumulativeRedemptionOrders": 267,
    "cumulativeRedemptionAmount": 6324.48
  }
]